rpg_map-0.1.0.dist-info/METADATA
rpg_map-0.1.0.dist-info/WHEEL
rpg_map-0.1.0.dist-info/licenses/LICENSE
rpg_map/__init__.py
rpg_map/__init__.pyi
rpg_map/py.typed
rpg_map/rpg_map.abi3.so
rpg_map-0.1.0.dist-info/RECORD
