Metadata-Version: 2.4
Name: rpg_map
Version: 0.1.0
Classifier: Programming Language :: Rust
Classifier: Programming Language :: Python :: Implementation :: CPython
Classifier: Programming Language :: Python :: Implementation :: PyPy
License-File: LICENSE
Summary: A zero dependency, lightweight and fast library to manipulate RPG images written in Rust.
Keywords: rpg,rpg-map,rpg-map-rs,rust,fast,lightweight,zero-dependency
License: MIT
Requires-Python: >=3.9
Project-URL: github, https://github.com/Kile/rpg_map
